oslogmerger/__init__.py
oslogmerger/oslogmerger.py
oslogmerger/probes/__init__.py
oslogmerger/probes/netprobe.py
oslogmerger/tests/__init__.py
oslogmerger/tests/base.py
oslogmerger/tests/unit/__init__.py
oslogmerger/tests/unit/test_oslogmerger.py
os_log_merger-1.2.1.dist-info/AUTHORS
os_log_merger-1.2.1.dist-info/LICENSE
os_log_merger-1.2.1.dist-info/METADATA
os_log_merger-1.2.1.dist-info/WHEEL
os_log_merger-1.2.1.dist-info/entry_points.txt
os_log_merger-1.2.1.dist-info/pbr.json
os_log_merger-1.2.1.dist-info/top_level.txt
os_log_merger-1.2.1.dist-info/RECORD
