Metadata-Version: 2.1
Name: os-log-merger
Version: 1.2.1
Summary: OpenStack Log merge tool
Home-page: https://github.com/openstack/os-log-merger
Author: OpenStack
Author-email: openstack-dev@lists.openstack.org
License: Apache Software License
Keywords: OpenStack log merger
Platform: UNKNOWN
Classifier: Environment :: OpenStack
Classifier: Intended Audience :: Developers
Classifier: Intended Audience :: System Administrators
Classifier: License :: OSI Approved :: Apache Software License
Classifier: Operating System :: POSIX :: Linux
Classifier: Programming Language :: Python
Classifier: Programming Language :: Python :: 2
Classifier: Programming Language :: Python :: 2.7
Classifier: Programming Language :: Python :: 3
Classifier: Programming Language :: Python :: 3.5
Classifier: Programming Language :: Python :: 3.6
Classifier: Programming Language :: Python :: 3.7
Classifier: Topic :: Utilities
Requires-Dist: pbr
Requires-Dist: python-dateutil
Requires-Dist: six
